oanda_backtest/__init__.py
oanda_backtest/oanda_backtest.py
oanda_backtest-0.2.2.dist-info/LICENSE.txt
oanda_backtest-0.2.2.dist-info/METADATA
oanda_backtest-0.2.2.dist-info/WHEEL
oanda_backtest-0.2.2.dist-info/top_level.txt
oanda_backtest-0.2.2.dist-info/RECORD
