Metadata-Version: 2.1
Name: oanda-backtest
Version: 0.2.2
Summary: oanda-backtest is a python library         for backtest with oanda fx rest api on Python 3.6 and above.
Home-page: https://github.com/10mohi6/oanda-backtest-python
Author: 10mohi6
Author-email: 10.mohi.6.y@gmail.com
License: MIT
Keywords: oanda backtest api python fx trade
Platform: UNKNOWN
Classifier: Development Status :: 4 - Beta
Classifier: Programming Language :: Python
Classifier: Programming Language :: Python :: 3
Classifier: Programming Language :: Python :: 3.6
Classifier: Programming Language :: Python :: 3.7
Classifier: Programming Language :: Python :: 3.8
Classifier: Intended Audience :: Developers
Classifier: Intended Audience :: Financial and Insurance Industry
Classifier: Operating System :: OS Independent
Classifier: Topic :: Office/Business :: Financial :: Investment
Classifier: License :: OSI Approved :: MIT License
Requires-Python: >=3.6.0
Requires-Dist: requests
Requires-Dist: numpy
Requires-Dist: pandas
Requires-Dist: matplotlib
